{
  "_class": "group",
  "do_objectID": "7EB13B10-9D4C-47C5-83A2-71CF44EED278",
  "exportOptions": {
    "_class": "exportOptions",
    "exportFormats": [
    ],
    "includedLayerIds": [
    ],
    "layerOptions": 0,
    "shouldTrim": false
  },
  "frame": {
    "_class": "rect",
    "constrainProportions": false,
    "height": 64,
    "width": 69,
    "x": 102,
    "y": 0
  },
  "hasClickThrough": false,
  "isFlippedHorizontal": false,
  "isFlippedVertical": false,
  "isLocked": false,
  "isVisible": true,
  "layerListExpandedType": 0,
  "layers": [
    {
      "class": "text",
      "id": "5C2C9E6E-FB70-42CC-A8A8-4A5AD23B78FE"
    },
    {
      "class": "text",
      "id": "82FB44ED-EC19-4E57-AD2A-D46A36DE035C"
    },
    {
      "class": "symbolInstance",
      "id": "EFC619F4-0DEE-4D25-875E-8C8F1458EBB5"
    }
  ],
  "name": "Stacked Group 9",
  "nameIsFixed": false,
  "resizingConstraint": 63,
  "resizingType": 0,
  "rotation": 0,
  "shouldBreakMaskChain": false,
  "style": {
    "_class": "style",
    "endDecorationType": 0,
    "miterLimit": 10,
    "startDecorationType": 0
  },
  "userInfo": {
    "com.animaapp.stc-sketch-plugin": {
      "kModelPropertiesKey": {
        "align": 0,
        "isCollapsing": 1,
        "spacing": 4,
        "stackType": 0
      },
      "kViewTypeKey": "ADModelStackView"
    }
  }
}